.coveragerc
.editorconfig
.gitattributes
CHANGES.rst
CONTRIBUTORS.rst
MANIFEST.in
README.rst
base.cfg
bobtemplate.cfg
bootstrap-buildout.py
buildout.cfg
constraints.txt
constraints_plone50.txt
constraints_plone51.txt
constraints_plone52.txt
requirements.txt
setup.cfg
setup.py
test_plone50.cfg
test_plone51.cfg
test_plone52.cfg
docs/LICENSE.GPL
docs/LICENSE.rst
docs/example1.jpg
docs/example2.jpg
src/collective/__init__.py
src/collective.editablemenu.egg-info/PKG-INFO
src/collective.editablemenu.egg-info/SOURCES.txt
src/collective.editablemenu.egg-info/dependency_links.txt
src/collective.editablemenu.egg-info/entry_points.txt
src/collective.editablemenu.egg-info/namespace_packages.txt
src/collective.editablemenu.egg-info/not-zip-safe
src/collective.editablemenu.egg-info/requires.txt
src/collective.editablemenu.egg-info/top_level.txt
src/collective/editablemenu/__init__.py
src/collective/editablemenu/configure.zcml
src/collective/editablemenu/interfaces.py
src/collective/editablemenu/setuphandlers.py
src/collective/editablemenu/testing.py
src/collective/editablemenu/upgrades.py
src/collective/editablemenu/upgrades.zcml
src/collective/editablemenu/Extensions/install.py
src/collective/editablemenu/browser/__init__.py
src/collective/editablemenu/browser/configure.zcml
src/collective/editablemenu/browser/controlpanel.py
src/collective/editablemenu/browser/interfaces.py
src/collective/editablemenu/browser/menu_support_view.py
src/collective/editablemenu/browser/viewlets.py
src/collective/editablemenu/browser/widgets.py
src/collective/editablemenu/browser/overrides/.gitkeep
src/collective/editablemenu/browser/static/delete_tab.png
src/collective/editablemenu/browser/static/editablemenu.png
src/collective/editablemenu/browser/static/dist/editablemenu.css
src/collective/editablemenu/browser/static/dist/editablemenu.css.map
src/collective/editablemenu/browser/static/dist/editablemenu.js
src/collective/editablemenu/browser/static/dist/editablemenu.js.map
src/collective/editablemenu/browser/static/dist/editablemenu.min.js
src/collective/editablemenu/browser/static/dist/editablemenu.min.js.map
src/collective/editablemenu/browser/static/dist/widget.css
src/collective/editablemenu/browser/static/dist/widget.css.map
src/collective/editablemenu/browser/static/dist/widget.js
src/collective/editablemenu/browser/static/dist/widget.js.map
