Metadata-Version: 2.1
Name: collective.editablemenu
Version: 2.3.0
Summary: A customizable dropdown menu
Home-page: https://github.com/RedTurtle/collective.editablemenu
Author: RedTurtle Technology
Author-email: sviluppoplone@redturtle.it
License: GPL version 2
Keywords: Python Plone Dropdown Menu Editable Customizable
Platform: UNKNOWN
Classifier: Environment :: Web Environment
Classifier: Framework :: Plone
Classifier: Framework :: Plone :: Addon
Classifier: Framework :: Plone :: 5.0
Classifier: Framework :: Plone :: 5.1
Classifier: Framework :: Plone :: 5.2
Classifier: Programming Language :: Python
Classifier: Programming Language :: Python :: 2.7
Classifier: Programming Language :: Python :: 3.6
Classifier: Programming Language :: Python :: 3.7
Classifier: Programming Language :: JavaScript
Classifier: Intended Audience :: Developers
Classifier: Operating System :: OS Independent
Classifier: License :: OSI Approved :: GNU General Public License v2 (GPLv2)
Classifier: Topic :: Software Development :: Libraries :: Python Modules
Provides-Extra: test
